<?xml version="1.0" encoding="UTF-8"?><pagina><testLC intentos="-1" urlRecurso="undefined" alineacion="" transSalida="" transEntrada="" vistaFla="testLC_KidsBox" h="924" w="740" y="0" x="0" idTexto="" nombre="test" id="test"><itemTestLC contenidoRelacionado="undefined" tipoActividad="RC" dificultad="0" intentos="-1" mostrarTG="undefined" desactivarBtnSiguiente="undefined" mostrarBtnMute="undefined" mostrarBtnPaginacion="undefined" mostrarBtnComprobar="undefined" mostrarRepetir="undefined" y_Navegacion="NaN" y_Check="786" idTeacherGuide="undefined" urlRecurso="undefined" activarSolucion="true" asiSeHace="undefined" alineacion="" transSalida="" transEntrada="" vistaFla="itemTestLC_KidsBox" h="924" w="740" y="0" x="0" idTexto="" nombre="Copia de Flechas 6 + audio" id="BVI5gM"><enunciado urlRecurso="" transSalida="" transEntrada="" vistaFla="enunciado_KidsBox" h="39" w="567.9" y="20" x="30" idTexto="21qg4" nombre="Enunciado 1" id="DYTGrp" /><origenFlechas posFlecha="right" ejemplo="false" correcto="4SvTNy" urlMP3="undefined" urlRecurso="undefined" alineacion="center" transSalida="" transEntrada="" vistaFla="origenFlechas_KidsBox" h="43" w="51.2" y="270" x="156" idTexto="NGVV8" nombre="Flechas 2" id="EuuJNT" /><origenFlechas posFlecha="right" ejemplo="false" correcto="npLR8p" urlMP3="undefined" urlRecurso="undefined" alineacion="center" transSalida="" transEntrada="" vistaFla="origenFlechas_KidsBox" h="43" w="51.2" y="402" x="156" idTexto="Xofws" nombre="Copia de Flechas 3" id="WuvJtK" /><origenFlechas posFlecha="right" ejemplo="false" correcto="4c4tuF" urlMP3="undefined" urlRecurso="undefined" alineacion="center" transSalida="" transEntrada="" vistaFla="origenFlechas_KidsBox" h="43" w="51.2" y="138" x="156" idTexto="mw176" nombre="Copia de Copia de Flechas 3" id="8UgPMR" /><origenFlechas posFlecha="right" ejemplo="false" correcto="1GqR1q" urlMP3="undefined" urlRecurso="undefined" alineacion="center" transSalida="" transEntrada="" vistaFla="origenFlechas_KidsBox" h="43" w="51.2" y="534" x="156" idTexto="3RNye" nombre="Flechas 3" id="PCbBBk" /><origenFlechas posFlecha="right" ejemplo="false" correcto="5UWXm5" urlMP3="undefined" urlRecurso="undefined" alineacion="center" transSalida="" transEntrada="" vistaFla="origenFlechas_KidsBox" h="43" w="51.2" y="665" x="156" idTexto="uKkjl" nombre="Copia de Flechas 3" id="46xQ7T" /><destinoArrastrar urlRecurso="" transSalida="" transEntrada="" vistaFla="destino_flechas_KidsBox" h="49" w="48.1" y="138" x="467" idTexto="" nombre="Destino 1" id="npLR8p" /><destinoArrastrar urlRecurso="" transSalida="" transEntrada="" vistaFla="destino_flechas_KidsBox" h="44" w="48.05" y="272" x="467" idTexto="" nombre="Destino 2" id="5UWXm5" /><destinoArrastrar urlRecurso="" transSalida="" transEntrada="" vistaFla="destino_flechas_KidsBox" h="47" w="47.05" y="533" x="467" idTexto="" nombre="Destino 4" id="4c4tuF" /><feedback urlMP3="undefined" urlRecurso="" tipoFeedback="act_positivo" transSalida="" transEntrada="" vistaFla="feedback_KidsBox" h="77" w="551.9" y="786" x="41.05" idTexto="" nombre="Feedback 1" id="u3LWcH" /><destinoArrastrar urlRecurso="" transSalida="" transEntrada="" vistaFla="destino_flechas_KidsBox" h="47" w="47.05" y="401" x="467" idTexto="" nombre="Destino 3" id="4SvTNy" /><destinoArrastrar urlRecurso="" transSalida="" transEntrada="" vistaFla="destino_flechas_KidsBox" h="47" w="47.05" y="665" x="467" idTexto="" nombre="Destino 5" id="1GqR1q" /><texto alignRight="false" textoBlanco="undefined" profesor="false" seleccionable="false" transSalida="" transEntrada="" vistaFla="texto_KidsBox" h="23" w="22" y="154" x="68" idTexto="gRRkS" nombre="Copia de Copia de Texto 1" id="fjM8jk" /><texto alignRight="false" textoBlanco="undefined" profesor="false" seleccionable="false" transSalida="" transEntrada="" vistaFla="texto_KidsBox" h="23" w="22" y="286" x="68" idTexto="jmJOX" nombre="Copia de Copia de Copia de Copia de Texto 1" id="s7QOnd" /><texto alignRight="false" textoBlanco="undefined" profesor="false" seleccionable="false" transSalida="" transEntrada="" vistaFla="texto_KidsBox" h="23" w="22" y="412" x="68" idTexto="kLLSt" nombre="Copia de Copia de Copia de Copia de Texto 1" id="k67C3P" /><texto alignRight="false" textoBlanco="undefined" profesor="false" seleccionable="false" transSalida="" transEntrada="" vistaFla="texto_KidsBox" h="23" w="22" y="544" x="68" idTexto="hoMkg" nombre="Copia de Copia de Copia de Copia de Copia de Texto 1" id="rQqPmr" /><texto alignRight="false" textoBlanco="undefined" profesor="false" seleccionable="false" transSalida="" transEntrada="" vistaFla="texto_KidsBox" h="23" w="22" y="683" x="68" idTexto="51n7m" nombre="Copia de Copia de Copia de Copia de Copia de Copia de Texto 1" id="jbb214" /><texto alignRight="false" textoBlanco="undefined" profesor="false" seleccionable="false" transSalida="" transEntrada="" vistaFla="texto_KidsBox" h="23" w="22" y="926" x="68" idTexto="csb7O" nombre="Copia de Copia de Copia de Copia de Copia de Copia de Copia de Texto 1" id="ytqMHM" /><elementoExt urlMP3="undefined" origeH="NaN" origeW="NaN" urlRecurso="kb2_pb1_u6_clil_int_ex2.png||986444d8-e738-4667-a543-1daa15a66d54" transSalida="" transEntrada="" vistaFla="elementoExterno_v2" h="647" w="554" y="93" x="95" nombre="imagen_oJsTjV" id="j7Ptn4" /></itemTestLC></testLC></pagina>