<?xml version="1.0" encoding="UTF-8"?><pagina><testLC intentos="-1" urlRecurso="undefined" alineacion="" transSalida="" transEntrada="" vistaFla="testLC_KidsBox" h="1101" w="740" y="0" x="0" idTexto="" nombre="test" id="test"><itemTestLC contenidoRelacionado="undefined" tipoActividad="RC" dificultad="0" intentos="-1" mostrarTG="undefined" desactivarBtnSiguiente="undefined" mostrarBtnMute="undefined" mostrarBtnPaginacion="undefined" mostrarBtnComprobar="false" mostrarRepetir="undefined" y_Navegacion="NaN" y_Check="814" idTeacherGuide="undefined" urlRecurso="undefined" activarSolucion="true" asiSeHace="undefined" alineacion="" transSalida="" transEntrada="" vistaFla="itemTestLC_KidsBox" h="1101" w="740" y="0" x="0" idTexto="" nombre=" RB_ secuence" id="fiLR8I"><enunciado urlRecurso="" transSalida="" transEntrada="" vistaFla="enunciado_KidsBox" h="40" w="588" y="20" x="30" idTexto="SrtRP" nombre="Copia de Enunciado 1" id="nV7Jdt" /><botonAudio autoPlay="undefined" feedback="false" transalumno="undefined" transcripcion="false" tipoBoton="0" xmlTranscript="undefined" urlRecurso="kb2_pb1_u8_int_ex12_a1.mp3||4a3cb926-4a79-400e-a0a2-f77d74860ef8" transSalida="" transEntrada="" vistaFla="botonAudio_KidsBox" h="50" w="163" y="93" x="30" idTexto="" nombre="audio 1" id="FRwvof" /><elementoExt urlMP3="undefined" origeH="NaN" origeW="NaN" urlRecurso="kb2_pb1_u8_ex12_01.jpg||749f0c65-bd15-49fa-9999-975258b420fc" transSalida="" transEntrada="" vistaFla="elementoExterno_v2" h="766" w="700" y="176" x="20" nombre="imagen_JWdRFY" id="imagen_JWdRFY" /><feedback urlMP3="undefined" urlRecurso="" tipoFeedback="act_positivo" transSalida="" transEntrada="" vistaFla="feedback_KidsBox" h="77" w="551.9" y="991" x="41.05" idTexto="" nombre="Copia de Feedback 1" id="X4WEcR" /><simboloRBSeleccionOrdenar correctPos="3" transSalida="" transEntrada="" vistaFla="rdSeleccionOrdenar_KidsBox" h="100" w="100" y="172" x="26.2" idTexto="" nombre="Listen and Point 1" id="HxMnko" /><simboloRBSeleccionOrdenar correctPos="5" transSalida="" transEntrada="" vistaFla="rdSeleccionOrdenar_KidsBox" h="100" w="100" y="429" x="26" idTexto="" nombre="Listen and Point2" id="IYX3Oo" /><simboloRBSeleccionOrdenar correctPos="2" transSalida="" transEntrada="" vistaFla="rdSeleccionOrdenar_KidsBox" h="100" w="100" y="431" x="383" idTexto="" nombre="Listen and Point 3" id="nP3mqt" /><simboloRBSeleccionOrdenar correctPos="4" transSalida="" transEntrada="" vistaFla="rdSeleccionOrdenar_KidsBox" h="100" w="100" y="690" x="29.2" idTexto="" nombre=" Listen and Point 4" id="Jt4PDO" /><simboloRBSeleccionOrdenar correctPos="1" transSalida="" transEntrada="" vistaFla="rdSeleccionOrdenar_KidsBox" h="100" w="100" y="690" x="383" idTexto="" nombre="Copia de Copia de Listen and Point 1" id="jBPMWD" /></itemTestLC></testLC></pagina>